{
    "ambientocclusion": false,
    "display": {
        "gui": {
            "rotation": [ 30, 45, 0 ],
            "translation": [ 0, 0, 0 ],
            "scale": [ 0.625, 0.625, 0.625 ]
        },
        "ground": {
            "rotation": [ 0, 0, 0 ],
            "translation": [ 0, 3, 0 ],
            "scale": [ 0.25, 0.25, 0.25 ]
        },
        "fixed": {
            "rotation": [ 0, 180, 0 ],
            "translation": [ 0, 0, 0 ],
            "scale": [ 1, 1, 1 ]
        },
        "head": {
            "rotation": [ 0, 180, 0 ],
            "translation": [ 0, 0, 0 ],
            "scale": [ 1, 1, 1 ]
        },
        "firstperson_righthand": {
            "rotation": [ 0, 315, 0 ],
            "translation": [ 0, 2.5, 0 ],
            "scale": [ 0.4, 0.4, 0.4 ]
        },
        "thirdperson_righthand": {
            "rotation": [ 75, 315, 0 ],
            "translation": [ 0, 2.5, 0 ],
            "scale": [ 0.375, 0.375, 0.375 ]
        }
    },
    "elements": [
        {
            "name": "Cube",
            "from": [ 2, 0, 0 ], 
            "to": [ 16, 2, 2 ], 
            "faces": {
                "north": { "texture": "#frame", "uv": [ 2, 0, 16, 2 ], "rotation": 180 },
                "east": { "texture": "#frame", "uv": [ 0, 0, 2, 2 ], "rotation": 180 },
                "south": { "texture": "#frame", "uv": [ 1, 10, 15, 12 ] },
                "up": { "texture": "#frame", "uv": [ 1, 1, 15, 3 ] },
                "down": { "texture": "#frame", "uv": [ 0, 0, 14, 2 ], "rotation": 180 }
            }
        },
        {
            "name": "Cube",
            "from": [ 0, 0, 0 ], 
            "to": [ 2, 2, 14 ], 
            "faces": {
                "north": { "texture": "#frame", "uv": [ 0, 0, 2, 2 ], "rotation": 180 },
                "east": { "texture": "#frame", "uv": [ 1, 7, 15, 9 ] },
                "west": { "texture": "#frame", "uv": [ 2, 0, 16, 2 ], "rotation": 180 },
                "up": { "texture": "#frame", "uv": [ 7, 1, 9, 15 ] },
                "down": { "texture": "#frame", "uv": [ 0, 2, 2, 16 ] }
            }
        },
        {
            "name": "Cube",
            "from": [ 0, 0, 14 ], 
            "to": [ 14, 2, 16 ], 
            "faces": {
                "north": { "texture": "#frame", "uv": [ 1, 2, 15, 4 ] },
                "south": { "texture": "#frame", "uv": [ 2, 0, 16, 2 ], "rotation": 180 },
                "west": { "texture": "#frame", "uv": [ 0, 0, 2, 2 ], "rotation": 180 },
                "up": { "texture": "#frame", "uv": [ 1, 2, 15, 4 ] },
                "down": { "texture": "#frame", "uv": [ 0, 0, 14, 2 ] }
            }
        },
        {
            "name": "Cube",
            "from": [ 14, 0, 2 ], 
            "to": [ 16, 2, 16 ], 
            "faces": {
                "east": { "texture": "#frame", "uv": [ 2, 0, 16, 2 ], "rotation": 180 },
                "south": { "texture": "#frame", "uv": [ 0, 0, 2, 2 ], "rotation": 180 },
                "west": { "texture": "#frame", "uv": [ 1, 2, 15, 4 ] },
                "up": { "texture": "#frame", "uv": [ 7, 1, 9, 15 ] },
                "down": { "texture": "#frame", "uv": [ 0, 2, 2, 16 ], "rotation": 180 }
            }
        },
        {
            "name": "Cube",
            "from": [ 2, 14, 0 ], 
            "to": [ 16, 16, 2 ], 
            "faces": {
                "north": { "texture": "#frame", "uv": [ 0, 0, 14, 2 ] },
                "east": { "texture": "#frame", "uv": [ 0, 0, 2, 2 ], "rotation": 90 },
                "south": { "texture": "#frame", "uv": [ 1, 10, 15, 12 ] },
                "up": { "texture": "#frame", "uv": [ 2, 0, 16, 2 ] },
                "down": { "texture": "#frame", "uv": [ 1, 8, 15, 10 ], "rotation": 180 }
            }
        },
        {
            "name": "Cube",
            "from": [ 0, 14, 0 ], 
            "to": [ 2, 16, 14 ], 
            "faces": {
                "north": { "texture": "#frame", "uv": [ 0, 0, 2, 2 ], "rotation": 90 },
                "east": { "texture": "#frame", "uv": [ 1, 7, 15, 9 ] },
                "west": { "texture": "#frame", "uv": [ 0, 0, 14, 2 ] },
                "up": { "texture": "#frame", "uv": [ 0, 0, 2, 14 ] },
                "down": { "texture": "#frame", "uv": [ 7, 1, 9, 15 ] }
            }
        },
        {
            "name": "Cube",
            "from": [ 0, 14, 14 ], 
            "to": [ 14, 16, 16 ], 
            "faces": {
                "north": { "texture": "#frame", "uv": [ 1, 2, 15, 4 ] },
                "south": { "texture": "#frame", "uv": [ 0, 0, 14, 2 ] },
                "west": { "texture": "#frame", "uv": [ 0, 0, 2, 2 ], "rotation": 90 },
                "up": { "texture": "#frame", "uv": [ 0, 14, 14, 16 ] },
                "down": { "texture": "#frame", "uv": [ 1, 2, 15, 4 ] }
            }
        },
        {
            "name": "Cube",
            "from": [ 14, 14, 2 ], 
            "to": [ 16, 16, 16 ], 
            "faces": {
                "east": { "texture": "#frame", "uv": [ 0, 0, 14, 2 ] },
                "south": { "texture": "#frame", "uv": [ 0, 0, 2, 2 ], "rotation": 90 },
                "west": { "texture": "#frame", "uv": [ 1, 2, 15, 4 ] },
                "up": { "texture": "#frame", "uv": [ 14, 2, 16, 16 ] },
                "down": { "texture": "#frame", "uv": [ 2, 1, 4, 15 ], "rotation": 180 }
            }
        },
        {
            "name": "Cube",
            "from": [ 0, 2, 0 ], 
            "to": [ 2, 14, 2 ], 
            "faces": {
                "north": { "texture": "#frame", "uv": [ 14, 1, 16, 13 ] },
                "east": { "texture": "#frame", "uv": [ 1, 1, 3, 13 ] },
                "south": { "texture": "#frame", "uv": [ 1, 1, 3, 13 ] },
                "west": { "texture": "#frame", "uv": [ 0, 1, 2, 13 ] }
            }
        },
        {
            "name": "Cube",
            "from": [ 14, 2, 0 ], 
            "to": [ 16, 14, 2 ], 
            "faces": {
                "north": { "texture": "#frame", "uv": [ 0, 1, 2, 13 ] },
                "east": { "texture": "#frame", "uv": [ 14, 1, 16, 13 ] },
                "south": { "texture": "#frame", "uv": [ 1, 1, 3, 13 ] },
                "west": { "texture": "#frame", "uv": [ 1, 1, 3, 13 ] }
            }
        },
        {
            "name": "Cube",
            "from": [ 14, 2, 14 ], 
            "to": [ 16, 14, 16 ], 
            "faces": {
                "north": { "texture": "#frame", "uv": [ 1, 1, 3, 13 ] },
                "east": { "texture": "#frame", "uv": [ 0, 1, 2, 13 ] },
                "south": { "texture": "#frame", "uv": [ 14, 1, 16, 13 ] },
                "west": { "texture": "#frame", "uv": [ 1, 1, 3, 13 ] }
            }
        },
        {
            "name": "Cube",
            "from": [ 0, 2, 14 ], 
            "to": [ 2, 14, 16 ], 
            "faces": {
                "north": { "texture": "#frame", "uv": [ 1, 1, 3, 13 ] },
                "east": { "texture": "#frame", "uv": [ 1, 1, 3, 13 ] },
                "south": { "texture": "#frame", "uv": [ 0, 1, 2, 13 ] },
                "west": { "texture": "#frame", "uv": [ 14, 1, 16, 13 ] }
            }
        },
        {
            "name": "Cube",
            "from": [ 1, 3, 2 ], 
            "to": [ 2, 13, 3 ], 
            "rotation": { "origin": [ 8, 8, 8 ], "axis": "x", "angle": 45.0 },
            "faces": {
                "north": { "texture": "#frame", "uv": [ 1, 1, 2, 11 ] },
                "east": { "texture": "#frame", "uv": [ 1, 1, 2, 11 ] },
                "south": { "texture": "#frame", "uv": [ 1, 1, 2, 11 ] },
                "west": { "texture": "#frame", "uv": [ 1, 1, 2, 11 ] },
                "up": { "texture": "#frame", "uv": [ 1, 1, 2, 2 ] },
                "down": { "texture": "#frame", "uv": [ 1, 1, 2, 2 ] }
            }
        },
        {
            "name": "Cube",
            "from": [ 1, 3, 2 ], 
            "to": [ 2, 13, 3 ], 
            "rotation": { "origin": [ 8, 8, 8 ], "axis": "x", "angle": -45.0 },
            "faces": {
                "north": { "texture": "#frame", "uv": [ 1, 1, 2, 11 ] },
                "east": { "texture": "#frame", "uv": [ 1, 1, 2, 11 ] },
                "south": { "texture": "#frame", "uv": [ 1, 1, 2, 11 ] },
                "west": { "texture": "#frame", "uv": [ 1, 1, 2, 11 ] },
                "up": { "texture": "#frame", "uv": [ 1, 1, 2, 2 ] },
                "down": { "texture": "#frame", "uv": [ 1, 1, 2, 2 ] }
            }
        },
        {
            "name": "Cube",
            "from": [ 14, 3, 2 ], 
            "to": [ 15, 13, 3 ], 
            "rotation": { "origin": [ 8, 8, 8 ], "axis": "x", "angle": -45.0 },
            "faces": {
                "north": { "texture": "#frame", "uv": [ 1, 1, 2, 11 ] },
                "east": { "texture": "#frame", "uv": [ 1, 1, 2, 11 ] },
                "south": { "texture": "#frame", "uv": [ 1, 1, 2, 11 ] },
                "west": { "texture": "#frame", "uv": [ 1, 1, 2, 11 ] },
                "up": { "texture": "#frame", "uv": [ 1, 1, 2, 2 ] },
                "down": { "texture": "#frame", "uv": [ 1, 1, 2, 2 ] }
            }
        },
        {
            "name": "Cube",
            "from": [ 14, 3, 2 ], 
            "to": [ 15, 13, 3 ], 
            "rotation": { "origin": [ 8, 8, 8 ], "axis": "x", "angle": 45.0 },
            "faces": {
                "north": { "texture": "#frame", "uv": [ 1, 1, 2, 11 ] },
                "east": { "texture": "#frame", "uv": [ 1, 1, 2, 11 ] },
                "south": { "texture": "#frame", "uv": [ 1, 1, 2, 11 ] },
                "west": { "texture": "#frame", "uv": [ 1, 1, 2, 11 ] },
                "up": { "texture": "#frame", "uv": [ 1, 1, 2, 2 ] },
                "down": { "texture": "#frame", "uv": [ 1, 1, 2, 2 ] }
            }
        },
        {
            "name": "Cube",
            "from": [ 14, 3, 13 ], 
            "to": [ 15, 13, 14 ], 
            "rotation": { "origin": [ 8, 8, 8 ], "axis": "x", "angle": 45.0 },
            "faces": {
                "north": { "texture": "#frame", "uv": [ 1, 1, 2, 11 ] },
                "east": { "texture": "#frame", "uv": [ 1, 1, 2, 11 ] },
                "south": { "texture": "#frame", "uv": [ 1, 1, 2, 11 ] },
                "west": { "texture": "#frame", "uv": [ 1, 1, 2, 11 ] },
                "up": { "texture": "#frame", "uv": [ 1, 1, 2, 2 ] },
                "down": { "texture": "#frame", "uv": [ 1, 1, 2, 2 ] }
            }
        },
        {
            "name": "Cube",
            "from": [ 14, 3, 13 ], 
            "to": [ 15, 13, 14 ], 
            "rotation": { "origin": [ 8, 8, 8 ], "axis": "x", "angle": -45.0 },
            "faces": {
                "north": { "texture": "#frame", "uv": [ 1, 1, 2, 11 ] },
                "east": { "texture": "#frame", "uv": [ 1, 1, 2, 11 ] },
                "south": { "texture": "#frame", "uv": [ 1, 1, 2, 11 ] },
                "west": { "texture": "#frame", "uv": [ 1, 1, 2, 11 ] },
                "up": { "texture": "#frame", "uv": [ 1, 1, 2, 2 ] },
                "down": { "texture": "#frame", "uv": [ 1, 1, 2, 2 ] }
            }
        },
        {
            "name": "Cube",
            "from": [ 1, 3, 13 ], 
            "to": [ 2, 13, 14 ], 
            "rotation": { "origin": [ 8, 8, 8 ], "axis": "x", "angle": -45.0 },
            "faces": {
                "north": { "texture": "#frame", "uv": [ 1, 1, 2, 11 ] },
                "east": { "texture": "#frame", "uv": [ 1, 1, 2, 11 ] },
                "south": { "texture": "#frame", "uv": [ 1, 1, 2, 11 ] },
                "west": { "texture": "#frame", "uv": [ 1, 1, 2, 11 ] },
                "up": { "texture": "#frame", "uv": [ 1, 1, 2, 2 ] },
                "down": { "texture": "#frame", "uv": [ 1, 1, 2, 2 ] }
            }
        },
        {
            "name": "Cube",
            "from": [ 1, 3, 13 ], 
            "to": [ 2, 13, 14 ], 
            "rotation": { "origin": [ 8, 8, 8 ], "axis": "x", "angle": 45.0 },
            "faces": {
                "north": { "texture": "#frame", "uv": [ 1, 1, 2, 11 ] },
                "east": { "texture": "#frame", "uv": [ 1, 1, 2, 11 ] },
                "south": { "texture": "#frame", "uv": [ 1, 1, 2, 11 ] },
                "west": { "texture": "#frame", "uv": [ 1, 1, 2, 11 ] },
                "up": { "texture": "#frame", "uv": [ 1, 1, 2, 2 ] },
                "down": { "texture": "#frame", "uv": [ 1, 1, 2, 2 ] }
            }
        },
        {
            "name": "Cube",
            "from": [ 2, 3, 14 ], 
            "to": [ 3, 13, 15 ], 
            "rotation": { "origin": [ 8, 8, 8 ], "axis": "z", "angle": 45.0 },
            "faces": {
                "north": { "texture": "#frame", "uv": [ 1, 1, 2, 11 ] },
                "east": { "texture": "#frame", "uv": [ 1, 1, 2, 11 ] },
                "south": { "texture": "#frame", "uv": [ 1, 1, 2, 11 ] },
                "west": { "texture": "#frame", "uv": [ 1, 1, 2, 11 ] },
                "up": { "texture": "#frame", "uv": [ 1, 1, 2, 2 ] },
                "down": { "texture": "#frame", "uv": [ 1, 1, 2, 2 ] }
            }
        },
        {
            "name": "Cube",
            "from": [ 2, 3, 14 ], 
            "to": [ 3, 13, 15 ], 
            "rotation": { "origin": [ 8, 8, 8 ], "axis": "z", "angle": -45.0 },
            "faces": {
                "north": { "texture": "#frame", "uv": [ 1, 1, 2, 11 ] },
                "east": { "texture": "#frame", "uv": [ 1, 1, 2, 11 ] },
                "south": { "texture": "#frame", "uv": [ 1, 1, 2, 11 ] },
                "west": { "texture": "#frame", "uv": [ 1, 1, 2, 11 ] },
                "up": { "texture": "#frame", "uv": [ 1, 1, 2, 2 ] },
                "down": { "texture": "#frame", "uv": [ 1, 1, 2, 2 ] }
            }
        },
        {
            "name": "Cube",
            "from": [ 2, 3, 1 ], 
            "to": [ 3, 13, 2 ], 
            "rotation": { "origin": [ 8, 8, 8 ], "axis": "z", "angle": 45.0 },
            "faces": {
                "north": { "texture": "#frame", "uv": [ 1, 1, 2, 11 ] },
                "east": { "texture": "#frame", "uv": [ 1, 1, 2, 11 ] },
                "south": { "texture": "#frame", "uv": [ 1, 1, 2, 11 ] },
                "west": { "texture": "#frame", "uv": [ 1, 1, 2, 11 ] },
                "up": { "texture": "#frame", "uv": [ 1, 1, 2, 2 ] },
                "down": { "texture": "#frame", "uv": [ 1, 1, 2, 2 ] }
            }
        },
        {
            "name": "Cube",
            "from": [ 2, 3, 1 ], 
            "to": [ 3, 13, 2 ], 
            "rotation": { "origin": [ 8, 8, 8 ], "axis": "z", "angle": -45.0 },
            "faces": {
                "north": { "texture": "#frame", "uv": [ 1, 1, 2, 11 ] },
                "east": { "texture": "#frame", "uv": [ 1, 1, 2, 11 ] },
                "south": { "texture": "#frame", "uv": [ 1, 1, 2, 11 ] },
                "west": { "texture": "#frame", "uv": [ 1, 1, 2, 11 ] },
                "up": { "texture": "#frame", "uv": [ 1, 1, 2, 2 ] },
                "down": { "texture": "#frame", "uv": [ 1, 1, 2, 2 ] }
            }
        },
        {
            "name": "Cube",
            "from": [ 13, 3, 1 ], 
            "to": [ 14, 13, 2 ], 
            "rotation": { "origin": [ 8, 8, 8 ], "axis": "z", "angle": -45.0 },
            "faces": {
                "north": { "texture": "#frame", "uv": [ 1, 1, 2, 11 ] },
                "east": { "texture": "#frame", "uv": [ 1, 1, 2, 11 ] },
                "south": { "texture": "#frame", "uv": [ 1, 1, 2, 11 ] },
                "west": { "texture": "#frame", "uv": [ 1, 1, 2, 11 ] },
                "up": { "texture": "#frame", "uv": [ 1, 1, 2, 2 ] },
                "down": { "texture": "#frame", "uv": [ 1, 1, 2, 2 ] }
            }
        },
        {
            "name": "Cube",
            "from": [ 13, 3, 1 ], 
            "to": [ 14, 13, 2 ], 
            "rotation": { "origin": [ 8, 8, 8 ], "axis": "z", "angle": 45.0 },
            "faces": {
                "north": { "texture": "#frame", "uv": [ 1, 1, 2, 11 ] },
                "east": { "texture": "#frame", "uv": [ 1, 1, 2, 11 ] },
                "south": { "texture": "#frame", "uv": [ 1, 1, 2, 11 ] },
                "west": { "texture": "#frame", "uv": [ 1, 1, 2, 11 ] },
                "up": { "texture": "#frame", "uv": [ 1, 1, 2, 2 ] },
                "down": { "texture": "#frame", "uv": [ 1, 1, 2, 2 ] }
            }
        },
        {
            "name": "Cube",
            "from": [ 13, 3, 14 ], 
            "to": [ 14, 13, 15 ], 
            "rotation": { "origin": [ 8, 8, 8 ], "axis": "z", "angle": 45.0 },
            "faces": {
                "north": { "texture": "#frame", "uv": [ 1, 1, 2, 11 ] },
                "east": { "texture": "#frame", "uv": [ 1, 1, 2, 11 ] },
                "south": { "texture": "#frame", "uv": [ 1, 1, 2, 11 ] },
                "west": { "texture": "#frame", "uv": [ 1, 1, 2, 11 ] },
                "up": { "texture": "#frame", "uv": [ 1, 1, 2, 2 ] },
                "down": { "texture": "#frame", "uv": [ 1, 1, 2, 2 ] }
            }
        },
        {
            "name": "Cube",
            "from": [ 13, 3, 14 ], 
            "to": [ 14, 13, 15 ], 
            "rotation": { "origin": [ 8, 8, 8 ], "axis": "z", "angle": -45.0 },
            "faces": {
                "north": { "texture": "#frame", "uv": [ 1, 1, 2, 11 ] },
                "east": { "texture": "#frame", "uv": [ 1, 1, 2, 11 ] },
                "south": { "texture": "#frame", "uv": [ 1, 1, 2, 11 ] },
                "west": { "texture": "#frame", "uv": [ 1, 1, 2, 11 ] },
                "up": { "texture": "#frame", "uv": [ 1, 1, 2, 2 ] },
                "down": { "texture": "#frame", "uv": [ 1, 1, 2, 2 ] }
            }
        },
        {
            "name": "Cube",
            "from": [ 3, 14, 13 ], 
            "to": [ 13, 15, 14 ], 
            "rotation": { "origin": [ 8, 8, 8 ], "axis": "y", "angle": 45.0 },
            "faces": {
                "north": { "texture": "#frame", "uv": [ 1, 1, 11, 2 ] },
                "east": { "texture": "#frame", "uv": [ 1, 1, 2, 2 ] },
                "south": { "texture": "#frame", "uv": [ 1, 1, 11, 2 ] },
                "west": { "texture": "#frame", "uv": [ 1, 1, 2, 2 ] },
                "up": { "texture": "#frame", "uv": [ 1, 1, 11, 2 ] },
                "down": { "texture": "#frame", "uv": [ 1, 1, 11, 2 ] }
            }
        },
        {
            "name": "Cube",
            "from": [ 3, 1, 13 ], 
            "to": [ 13, 2, 14 ], 
            "rotation": { "origin": [ 8, 8, 8 ], "axis": "y", "angle": 45.0 },
            "faces": {
                "north": { "texture": "#frame", "uv": [ 1, 1, 11, 2 ] },
                "east": { "texture": "#frame", "uv": [ 1, 1, 2, 2 ] },
                "south": { "texture": "#frame", "uv": [ 1, 1, 11, 2 ] },
                "west": { "texture": "#frame", "uv": [ 1, 1, 2, 2 ] },
                "up": { "texture": "#frame", "uv": [ 1, 1, 11, 2 ] },
                "down": { "texture": "#frame", "uv": [ 1, 1, 11, 2 ] }
            }
        },
        {
            "name": "Cube",
            "from": [ 3, 1, 13 ], 
            "to": [ 13, 2, 14 ], 
            "rotation": { "origin": [ 8, 8, 8 ], "axis": "y", "angle": -45.0 },
            "faces": {
                "north": { "texture": "#frame", "uv": [ 1, 1, 11, 2 ] },
                "east": { "texture": "#frame", "uv": [ 1, 1, 2, 2 ] },
                "south": { "texture": "#frame", "uv": [ 1, 1, 11, 2 ] },
                "west": { "texture": "#frame", "uv": [ 1, 1, 2, 2 ] },
                "up": { "texture": "#frame", "uv": [ 1, 1, 11, 2 ] },
                "down": { "texture": "#frame", "uv": [ 1, 1, 11, 2 ] }
            }
        },
        {
            "name": "Cube",
            "from": [ 3, 14, 13 ], 
            "to": [ 13, 15, 14 ], 
            "rotation": { "origin": [ 8, 8, 8 ], "axis": "y", "angle": -45.0 },
            "faces": {
                "north": { "texture": "#frame", "uv": [ 1, 1, 11, 2 ] },
                "east": { "texture": "#frame", "uv": [ 1, 1, 2, 2 ] },
                "south": { "texture": "#frame", "uv": [ 1, 1, 11, 2 ] },
                "west": { "texture": "#frame", "uv": [ 1, 1, 2, 2 ] },
                "up": { "texture": "#frame", "uv": [ 1, 1, 11, 2 ] },
                "down": { "texture": "#frame", "uv": [ 1, 1, 11, 2 ] }
            }
        },
        {
            "name": "Cube",
            "from": [ 3, 14, 2 ], 
            "to": [ 13, 15, 3 ], 
            "rotation": { "origin": [ 8, 8, 8 ], "axis": "y", "angle": 45.0 },
            "faces": {
                "north": { "texture": "#frame", "uv": [ 1, 1, 11, 2 ] },
                "east": { "texture": "#frame", "uv": [ 1, 1, 2, 2 ] },
                "south": { "texture": "#frame", "uv": [ 1, 1, 11, 2 ] },
                "west": { "texture": "#frame", "uv": [ 1, 1, 2, 2 ] },
                "up": { "texture": "#frame", "uv": [ 1, 1, 11, 2 ] },
                "down": { "texture": "#frame", "uv": [ 1, 1, 11, 2 ] }
            }
        },
        {
            "name": "Cube",
            "from": [ 3, 1, 2 ], 
            "to": [ 13, 2, 3 ], 
            "rotation": { "origin": [ 8, 8, 8 ], "axis": "y", "angle": 45.0 },
            "faces": {
                "north": { "texture": "#frame", "uv": [ 1, 1, 11, 2 ] },
                "east": { "texture": "#frame", "uv": [ 1, 1, 2, 2 ] },
                "south": { "texture": "#frame", "uv": [ 1, 1, 11, 2 ] },
                "west": { "texture": "#frame", "uv": [ 1, 1, 2, 2 ] },
                "up": { "texture": "#frame", "uv": [ 1, 1, 11, 2 ] },
                "down": { "texture": "#frame", "uv": [ 1, 1, 11, 2 ] }
            }
        },
        {
            "name": "Cube",
            "from": [ 3, 1, 2 ], 
            "to": [ 13, 2, 3 ], 
            "rotation": { "origin": [ 8, 8, 8 ], "axis": "y", "angle": -45.0 },
            "faces": {
                "north": { "texture": "#frame", "uv": [ 1, 1, 11, 2 ] },
                "east": { "texture": "#frame", "uv": [ 1, 1, 2, 2 ] },
                "south": { "texture": "#frame", "uv": [ 1, 1, 11, 2 ] },
                "west": { "texture": "#frame", "uv": [ 1, 1, 2, 2 ] },
                "up": { "texture": "#frame", "uv": [ 1, 1, 11, 2 ] },
                "down": { "texture": "#frame", "uv": [ 1, 1, 11, 2 ] }
            }
        },
        {
            "name": "Cube",
            "from": [ 3, 14, 2 ], 
            "to": [ 13, 15, 3 ], 
            "rotation": { "origin": [ 8, 8, 8 ], "axis": "y", "angle": -45.0 },
            "faces": {
                "north": { "texture": "#frame", "uv": [ 1, 1, 11, 2 ] },
                "east": { "texture": "#frame", "uv": [ 1, 1, 2, 2 ] },
                "south": { "texture": "#frame", "uv": [ 1, 1, 11, 2 ] },
                "west": { "texture": "#frame", "uv": [ 1, 1, 2, 2 ] },
                "up": { "texture": "#frame", "uv": [ 1, 1, 11, 2 ] },
                "down": { "texture": "#frame", "uv": [ 1, 1, 11, 2 ] }
            }
        }
    ]
}